{
  "version": "5",
  "dialect": "mysql",
  "id": "858ad744-ec50-41d2-b19f-2359174b2210",
  "prevId": "00000000-0000-0000-0000-000000000000",
  "tables": {
    "user_key": {
      "name": "user_key",
      "columns": {
        "id": {
          "name": "id",
          "type": "varchar(255)",
          "primaryKey": false,
          "notNull": true,
          "autoincrement": false
        },
        "user_id": {
          "name": "user_id",
          "type": "varchar(15)",
          "primaryKey": false,
          "notNull": true,
          "autoincrement": false
        },
        "hashed_password": {
          "name": "hashed_password",
          "type": "varchar(255)",
          "primaryKey": false,
          "notNull": false,
          "autoincrement": false
        }
      },
      "indexes": {},
      "foreignKeys": {},
      "compositePrimaryKeys": {
        "user_key_id": {
          "name": "user_key_id",
          "columns": [
            "id"
          ]
        }
      },
      "uniqueConstraints": {}
    },
    "user_session": {
      "name": "user_session",
      "columns": {
        "id": {
          "name": "id",
          "type": "varchar(128)",
          "primaryKey": false,
          "notNull": true,
          "autoincrement": false
        },
        "user_id": {
          "name": "user_id",
          "type": "varchar(15)",
          "primaryKey": false,
          "notNull": true,
          "autoincrement": false
        },
        "active_expires": {
          "name": "active_expires",
          "type": "bigint",
          "primaryKey": false,
          "notNull": true,
          "autoincrement": false
        },
        "idle_expires": {
          "name": "idle_expires",
          "type": "bigint",
          "primaryKey": false,
          "notNull": true,
          "autoincrement": false
        }
      },
      "indexes": {},
      "foreignKeys": {},
      "compositePrimaryKeys": {
        "user_session_id": {
          "name": "user_session_id",
          "columns": [
            "id"
          ]
        }
      },
      "uniqueConstraints": {}
    },
    "auth_user": {
      "name": "auth_user",
      "columns": {
        "id": {
          "name": "id",
          "type": "varchar(15)",
          "primaryKey": false,
          "notNull": true,
          "autoincrement": false
        },
        "name": {
          "name": "name",
          "type": "varchar(255)",
          "primaryKey": false,
          "notNull": false,
          "autoincrement": false
        },
        "email": {
          "name": "email",
          "type": "varchar(255)",
          "primaryKey": false,
          "notNull": false,
          "autoincrement": false
        },
        "username": {
          "name": "username",
          "type": "varchar(255)",
          "primaryKey": false,
          "notNull": false,
          "autoincrement": false
        }
      },
      "indexes": {},
      "foreignKeys": {},
      "compositePrimaryKeys": {
        "auth_user_id": {
          "name": "auth_user_id",
          "columns": [
            "id"
          ]
        }
      },
      "uniqueConstraints": {}
    },
    "subscriptions": {
      "name": "subscriptions",
      "columns": {
        "user_id": {
          "name": "user_id",
          "type": "varchar(255)",
          "primaryKey": false,
          "notNull": true,
          "autoincrement": false
        },
        "stripe_customer_id": {
          "name": "stripe_customer_id",
          "type": "varchar(255)",
          "primaryKey": false,
          "notNull": true,
          "autoincrement": false
        },
        "stripe_subscription_id": {
          "name": "stripe_subscription_id",
          "type": "varchar(255)",
          "primaryKey": false,
          "notNull": false,
          "autoincrement": false
        },
        "stripe_price_id": {
          "name": "stripe_price_id",
          "type": "varchar(255)",
          "primaryKey": false,
          "notNull": false,
          "autoincrement": false
        },
        "stripe_current_period_end": {
          "name": "stripe_current_period_end",
          "type": "timestamp",
          "primaryKey": false,
          "notNull": false,
          "autoincrement": false
        }
      },
      "indexes": {},
      "foreignKeys": {},
      "compositePrimaryKeys": {
        "subscriptions_user_id_stripe_customer_id_pk": {
          "name": "subscriptions_user_id_stripe_customer_id_pk",
          "columns": [
            "user_id",
            "stripe_customer_id"
          ]
        }
      },
      "uniqueConstraints": {
        "subscriptions_user_id_unique": {
          "name": "subscriptions_user_id_unique",
          "columns": [
            "user_id"
          ]
        },
        "subscriptions_stripe_customer_id_unique": {
          "name": "subscriptions_stripe_customer_id_unique",
          "columns": [
            "stripe_customer_id"
          ]
        },
        "subscriptions_stripe_subscription_id_unique": {
          "name": "subscriptions_stripe_subscription_id_unique",
          "columns": [
            "stripe_subscription_id"
          ]
        }
      }
    }
  },
  "schemas": {},
  "_meta": {
    "schemas": {},
    "tables": {},
    "columns": {}
  }
}